{
  "$schema": "http://json-schema.org/draft-07/schema#",
  "$id": "https://plugins.dprint.dev/kjanat/dprint-plugin-svg/0.2.0/schema.json",
  "title": "Top-level configuration schema for the dprint SVG plugin.",
  "description": "All fields are optional — omitted values fall back to dprint global\nconfig or built-in defaults.",
  "type": "object",
  "properties": {
    "attributeLayout": {
      "description": "Attribute line-breaking strategy.",
      "anyOf": [
        {
          "$ref": "#/definitions/AttributeLayoutConfig"
        },
        {
          "type": "null"
        }
      ]
    },
    "attributeSort": {
      "description": "Attribute ordering strategy.",
      "anyOf": [
        {
          "$ref": "#/definitions/AttributeSortConfig"
        },
        {
          "type": "null"
        }
      ]
    },
    "attributesPerLine": {
      "description": "Maximum number of attributes per line in multi-line mode.",
      "type": [
        "integer",
        "null"
      ],
      "format": "uint32",
      "minimum": 1
    },
    "blankLines": {
      "description": "How blank lines between sibling elements are handled.",
      "anyOf": [
        {
          "$ref": "#/definitions/BlankLinesConfig"
        },
        {
          "type": "null"
        }
      ]
    },
    "formatEmbeddedContent": {
      "description": "Whether to delegate embedded content (CSS, JS, HTML) to host plugins.",
      "type": [
        "boolean",
        "null"
      ]
    },
    "indentWidth": {
      "description": "Indent width when useTabs is false.",
      "type": [
        "integer",
        "null"
      ],
      "format": "uint8",
      "minimum": 1,
      "maximum": 255
    },
    "lineWidth": {
      "description": "Fallback line width for formatting decisions when maxInlineTagWidth is\nnot provided.",
      "type": [
        "integer",
        "null"
      ],
      "format": "uint32",
      "minimum": 1
    },
    "locked": {
      "description": "Whether the configuration is not allowed to be overridden or extended.",
      "type": [
        "boolean",
        "null"
      ]
    },
    "maxInlineTagWidth": {
      "description": "Maximum inline tag width before wrapping attributes or children.",
      "type": [
        "integer",
        "null"
      ],
      "format": "uint32",
      "minimum": 1
    },
    "newLineKind": {
      "description": "The newline kind to write.",
      "anyOf": [
        {
          "$ref": "#/definitions/NewLineKindConfig"
        },
        {
          "type": "null"
        }
      ]
    },
    "quoteStyle": {
      "description": "Quote style for attribute values.",
      "anyOf": [
        {
          "$ref": "#/definitions/QuoteStyleConfig"
        },
        {
          "type": "null"
        }
      ]
    },
    "spaceBeforeSelfClose": {
      "description": "Whether to include a space before '/>' in self-closing tags.",
      "type": [
        "boolean",
        "null"
      ]
    },
    "textContent": {
      "description": "How text-node whitespace is handled.",
      "anyOf": [
        {
          "$ref": "#/definitions/TextContentModeConfig"
        },
        {
          "type": "null"
        }
      ]
    },
    "useTabs": {
      "description": "Use tabs for indentation instead of spaces.",
      "type": [
        "boolean",
        "null"
      ]
    },
    "wrappedAttributeIndent": {
      "description": "Indent style for wrapped attributes.",
      "anyOf": [
        {
          "$ref": "#/definitions/WrappedAttributeIndentConfig"
        },
        {
          "type": "null"
        }
      ]
    }
  },
  "definitions": {
    "AttributeLayoutConfig": {
      "title": "Attribute wrapping mode exposed in the plugin config.",
      "description": "Maps 1:1 to [`svg_format::AttributeLayout`].\n\n```svg\n<!-- auto: wraps when inline exceeds maxInlineTagWidth -->\n<linearGradient\n    id=\"sky\"\n    x1=\"0%\"\n    y1=\"0%\">\n</linearGradient>\n\n<!-- single-line: always one line -->\n<linearGradient id=\"sky\" x1=\"0%\" y1=\"0%\"></linearGradient>\n\n<!-- multi-line: always wrap -->\n<rect\n    id=\"box\"\n    x=\"10\" />\n```",
      "oneOf": [
        {
          "description": "Wrap only when inline width exceeds `maxInlineTagWidth`.",
          "type": "string",
          "const": "auto"
        },
        {
          "description": "Always keep all attributes on one line.",
          "type": "string",
          "const": "single-line"
        },
        {
          "description": "Always wrap attributes onto separate lines.",
          "type": "string",
          "const": "multi-line"
        }
      ]
    },
    "AttributeSortConfig": {
      "title": "Attribute ordering strategy exposed in the plugin config.",
      "description": "Maps 1:1 to [`svg_format::AttributeSort`].\n\n```svg\n<!-- input -->\n<rect y=\"20\" x=\"10\" height=\"50\" width=\"100\" id=\"box\" />\n\n<!-- canonical (default) -->\n<rect id=\"box\" x=\"10\" y=\"20\" width=\"100\" height=\"50\" />\n\n<!-- alphabetical -->\n<rect height=\"50\" id=\"box\" width=\"100\" x=\"10\" y=\"20\" />\n```",
      "oneOf": [
        {
          "description": "Keep original source order.",
          "type": "string",
          "const": "none"
        },
        {
          "description": "SVG-aware canonical grouping (id, class, geometry, presentation, ...).",
          "type": "string",
          "const": "canonical"
        },
        {
          "description": "Strict alphabetical order.",
          "type": "string",
          "const": "alphabetical"
        }
      ]
    },
    "BlankLinesConfig": {
      "title": "How blank lines between sibling elements are handled.",
      "description": "Maps 1:1 to [`svg_format::BlankLines`].\n\n```svg\n<!-- input -->\n<svg>\n    <rect />\n\n\n    <!--legend-->\n    <circle />\n</svg>\n\n<!-- remove: all gaps stripped -->\n<svg>\n    <rect />\n    <!--legend-->\n    <circle />\n</svg>\n\n<!-- truncate (default): 2+ collapsed to 1 -->\n<svg>\n    <rect />\n\n    <!--legend-->\n    <circle />\n</svg>\n\n<!-- insert: force gap between every sibling -->\n<svg>\n    <rect />\n\n    <!--legend-->\n\n    <circle />\n</svg>\n```",
      "oneOf": [
        {
          "description": "Strip all blank lines between siblings.",
          "type": "string",
          "const": "remove"
        },
        {
          "description": "Keep blank lines from source verbatim.",
          "type": "string",
          "const": "preserve"
        },
        {
          "description": "Collapse 2+ blank lines to exactly 1.",
          "type": "string",
          "const": "truncate"
        },
        {
          "description": "Force exactly 1 blank line between every sibling.",
          "type": "string",
          "const": "insert"
        }
      ]
    },
    "NewLineKindConfig": {
      "title": "Line ending style.",
      "oneOf": [
        {
          "description": "Detect from the source file.",
          "type": "string",
          "const": "auto"
        },
        {
          "description": "Unix-style `\\n`.",
          "type": "string",
          "const": "lf"
        },
        {
          "description": "Windows-style `\\r\\n`.",
          "type": "string",
          "const": "crlf"
        }
      ]
    },
    "QuoteStyleConfig": {
      "title": "Quoting strategy for attribute values.",
      "description": "Maps 1:1 to [`svg_format::QuoteStyle`].\n\n```svg\n<!-- preserve: keeps original -->\n<rect id='box' class=\"hero\" />\n\n<!-- double -->\n<rect id=\"box\" class=\"hero\" />\n\n<!-- single -->\n<rect id='box' class='hero' />\n```",
      "oneOf": [
        {
          "description": "Keep the original quote character.",
          "type": "string",
          "const": "preserve"
        },
        {
          "description": "Normalize to double quotes.",
          "type": "string",
          "const": "double"
        },
        {
          "description": "Normalize to single quotes.",
          "type": "string",
          "const": "single"
        }
      ]
    },
    "TextContentModeConfig": {
      "title": "How the formatter handles whitespace in text nodes.",
      "description": "Maps 1:1 to [`svg_format::TextContentMode`].\n\n```svg\n<!-- input -->\n<text>  hello   world  </text>\n\n<!-- collapse -->\n<text>\n    hello world\n</text>\n\n<!-- maintain (default): preserves relative indentation -->\n<text>\n    hello   world\n</text>\n\n<!-- prettify: trims each line -->\n<text>\n    hello   world\n</text>\n```",
      "oneOf": [
        {
          "description": "Collapse whitespace runs to single spaces.",
          "type": "string",
          "const": "collapse"
        },
        {
          "description": "Preserve relative indentation structure.",
          "type": "string",
          "const": "maintain"
        },
        {
          "description": "Trim each line and re-indent to SVG depth.",
          "type": "string",
          "const": "prettify"
        }
      ]
    },
    "WrappedAttributeIndentConfig": {
      "title": "Indentation strategy for wrapped attributes.",
      "description": "Maps 1:1 to [`svg_format::WrappedAttributeIndent`].\n\n```svg\n<!-- one-level (default) -->\n<linearGradient\n    id=\"sky\"\n    x1=\"0%\">\n</linearGradient>\n\n<!-- align-to-tag-name -->\n<linearGradient\n                id=\"sky\"\n                x1=\"0%\">\n</linearGradient>\n```",
      "oneOf": [
        {
          "description": "Indent one level deeper than the tag.",
          "type": "string",
          "const": "one-level"
        },
        {
          "description": "Align to the column after `<tagName `.",
          "type": "string",
          "const": "align-to-tag-name"
        }
      ]
    }
  }
}
